{
	"name": "nom",
	"group": "groupe",
	"message": "Cette liste est vide. <br>N'hésite pas à y contribuer.",
	"lbl_tv": "TV",
	"lbl_ova": "OAV/ONA/Spéciaux",
	"lbl_movie": "Films",
	"tv": [{
			"name": "18if",
			"image": "https://myanimelist.cdn-dena.com/images/anime/7/86743.jpg",
			"group": [{
				"status": "release",
				"detail": [{
					"name": "JeSuisMonteam"
				}]
			}]
		},
		{
			"name": "Action Heroine Cheer Fruits",
			"image": "https://myanimelist.cdn-dena.com/images/anime/12/86741.jpg",
			"group": [{
				"status": "simulcast",
				"detail": [{
					"name": "Anime Digital Network"
				}]
			}]
		},
		{
			"name": "Aho Girl",
			"image": "https://myanimelist.cdn-dena.com/images/anime/7/86665.jpg",
			"group": [{
				"status": "simulcast",
				"detail": [{
					"name": "Crunchyroll"
				}]
			}]
		},
		{
			"name": "Ballroom e Youkoso",
			"image": "https://myanimelist.cdn-dena.com/images/anime/5/86739.jpg",
			"group": [{
					"status": "release",
					"detail": [{
						"name": "Houkago Fansub"
					}]
				},
				{
					"status": "simulcast",
					"detail": [{
						"name": "Amazon Prime"
					}]
				}
			]
		},
		{
			"name": "Battle Girl High School",
			"image": "https://myanimelist.cdn-dena.com/images/anime/11/86646.jpg",
			"group": [{
				"status": "simulcast",
				"detail": [{
					"name": "Anime Digital Network"
				}]
			}]
		},
		{
			"name": "Centaur no Nayami",
			"image": "https://myanimelist.cdn-dena.com/images/anime/2/86767.jpg",
			"group": [{
				"status": "simulcast",
				"detail": [{
					"name": "Crunchyroll"
				}]
			}]
		},
		{
			"name": "Clione no Akari",
			"image": "https://myanimelist.cdn-dena.com/images/anime/3/84706.jpg",
			"group": []
		},
		{
			"name": "Dive!!",
			"image": "https://myanimelist.cdn-dena.com/images/anime/11/86744.jpg",
			"group": [{
					"status": "release",
					"detail": [{
						"name": "Mangakas Fansub"
					}]
				},
				{
					"status": "simulcast",
					"detail": [{
						"name": "Amazon Prime"
					}]
				}
			]
		},
		{
			"name": "Enmusubi no Youko-chan",
			"image": "https://myanimelist.cdn-dena.com/images/anime/4/76470.jpg",
			"group": [{
				"status": "simulcast",
				"detail": [{
					"name": "Crunchyroll"
				}]
			}]
		},
		{
			"name": "Fate/Apocrypha",
			"image": "https://myanimelist.cdn-dena.com/images/anime/9/86573.jpg",
			"group": [{
					"status": "release",
					"detail": [{
							"name": "Houkago Fansub"
						},
						{
							"name": "Manga Family"
						}
					]
				},
				{
					"status": "simulcast",
					"detail": [{
						"name": "Netflix"
					}]
				}
			]
		},
		{
			"name": "Gamers!",
			"image": "https://myanimelist.cdn-dena.com/images/anime/4/86828.jpg",
			"group": [{
				"status": "simulcast",
				"detail": [{
					"name": "Crunchyroll"
				}]
			}]
		},
		{
			"name": "Hajimete no Gal",
			"image": "https://myanimelist.cdn-dena.com/images/anime/3/84417.jpg",
			"group": [{
				"status": "simulcast",
				"detail": [{
					"name": "Crunchyroll"
				}]
			}]
		},
		{
			"name": "Hina Logi: From Luck & Logic",
			"image": "https://myanimelist.cdn-dena.com/images/anime/11/86576.jpg",
			"group": [{
				"status": "simulcast",
				"detail": [{
					"name": "Wakanim"
				}]
			}]
		},
		{
			"name": "Hitorijime My Hero",
			"image": "https://myanimelist.cdn-dena.com/images/anime/12/86825.jpg",
			"group": [{
				"status": "release",
				"detail": [{
					"name": "Circus Fansub"
				}]
			}]
		},
		{
			"name": "Ikemen Sengoku: Toki wo Kakeru ga Koi wa Hajimaranai",
			"image": "https://myanimelist.cdn-dena.com/images/anime/7/86054.jpg",
			"group": [{
				"status": "simulcast",
				"detail": [{
					"name": "Anime Digital Network"
				}]
			}]
		},
		{
			"name": "Isekai Shokudou",
			"image": "https://myanimelist.cdn-dena.com/images/anime/3/86666.jpg",
			"group": [{
				"status": "simulcast",
				"detail": [{
					"name": "Crunchyroll"
				}]
			}]
		},
		{
			"name": "Isekai wa Smartphone to Tomo ni.",
			"image": "https://myanimelist.cdn-dena.com/images/anime/7/86794.jpg",
			"group": [{
				"status": "simulcast",
				"detail": [{
					"name": "Crunchyroll"
				}]
			}]
		},
		{
			"name": "Jigoku Shoujo: Yoi no Togi",
			"image": "https://myanimelist.cdn-dena.com/images/anime/12/86962.jpg",
			"group": [{
				"status": "simulcast",
				"detail": [{
					"name": "Wakanim"
				}]
			}]
		},
		{
			"name": "Jikan no Shihaisha",
			"image": "https://myanimelist.cdn-dena.com/images/anime/3/86753.jpg",
			"group": [{
				"status": "simulcast",
				"detail": [{
					"name": "Crunchyroll"
				}]
			}]
		},
		{
			"name": "Kaito × Ansa",
			"image": "https://myanimelist.cdn-dena.com/images/anime/5/85063.jpg",
			"group": []
		},
		{
			"name": "Kakegurui",
			"image": "https://myanimelist.cdn-dena.com/images/anime/3/86578.jpg",
			"group": [{
					"status": "release",
					"detail": [{
						"name": "Despair-Paradise"
					}]
				},
				{
					"status": "simulcast",
					"detail": [{
						"name": "Netflix"
					}]
				}
			]
		},
		{
			"name": "Katsugeki/Touken Ranbu",
			"image": "https://myanimelist.cdn-dena.com/images/anime/11/83840.jpg",
			"group": [{
				"status": "simulcast",
				"detail": [{
					"name": "Wakanim"
				}]
			}]
		},
		{
			"name": "Keppeki Danshi! Aoyama-kun",
			"image": "https://myanimelist.cdn-dena.com/images/anime/9/86644.jpg",
			"group": [{
				"status": "simulcast",
				"detail": [{
					"name": "Crunchyroll"
				}]
			}]
		},
		{
			"name": "Knight's & Magic",
			"image": "https://myanimelist.cdn-dena.com/images/anime/5/85914.jpg",
			"group": [{
				"status": "simulcast",
				"detail": [{
					"name": "Wakanim"
				}]
			}]
		},
		{
			"name": "Koi to Uso",
			"image": "https://myanimelist.cdn-dena.com/images/anime/5/86663.jpg",
			"group": [{
				"status": "simulcast",
				"detail": [{
					"name": "Wakanim"
				}]
			}]
		},
		{
			"name": "Konbini Kareshi",
			"image": "https://myanimelist.cdn-dena.com/images/anime/4/86243.jpg",
			"group": [{
				"status": "simulcast",
				"detail": [{
					"name": "Crunchyroll"
				}]
			}]
		},
		{
			"name": "Made in Abyss",
			"image": "https://myanimelist.cdn-dena.com/images/anime/10/84985.jpg",
			"group": [{
				"status": "simulcast",
				"detail": [{
					"name": "Wakanim"
				}]
			}]
		},
		{
			"name": "Mahoujin Guru Guru (2017)",
			"image": "https://myanimelist.cdn-dena.com/images/anime/9/86835.jpg",
			"group": [{
				"status": "simulcast",
				"detail": [{
					"name": "Crunchyroll"
				}]
			}]
		},
		{
			"name": "Marvel Future Avengers",
			"image": "https://myanimelist.cdn-dena.com/images/anime/12/85994.jpg",
			"group": []
		},
		{
			"name": "Mori no Yousei: Kinoko no Musume",
			"image": "https://myanimelist.cdn-dena.com/images/anime/6/85153.jpg",
			"group": [{
				"status": "simulcast",
				"detail": [{
					"name": "Crunchyroll"
				}]
			}]
		},
		{
			"name": "Musashino!",
			"image": "https://myanimelist.cdn-dena.com/images/anime/6/85104.jpg",
			"group": []
		},
		{
			"name": "Musekinin Galaxy☆Tylor",
			"image": "https://myanimelist.cdn-dena.com/images/anime/13/86832.jpg",
			"group": [{
				"status": "simulcast",
				"detail": [{
					"name": "Crunchyroll"
				}]
			}]
		},
		{
			"name": "Nana Maru San Batsu",
			"image": "https://myanimelist.cdn-dena.com/images/anime/9/86731.jpg",
			"group": [{
				"status": "simulcast",
				"detail": [{
					"name": "Crunchyroll"
				}]
			}]
		},
		{
			"name": "Netsuzou TRap",
			"image": "https://myanimelist.cdn-dena.com/images/anime/10/86667.jpg",
			"group": [{
				"status": "simulcast",
				"detail": [{
					"name": "Crunchyroll"
				}]
			}]
		},
		{
			"name": "New Game!!",
			"image": "https://myanimelist.cdn-dena.com/images/anime/4/86790.jpg",
			"group": [{
					"status": "simulcast",
					"detail": [{
						"name": "Crunchyroll"
					}]
				},
				{
					"status": "simulcast",
					"detail": [{
						"name": "Crunchyroll"
					}]
				}
			]
		},
		{
			"name": "Nora to Oujo to Noraneko Heart",
			"image": "https://myanimelist.cdn-dena.com/images/anime/3/85868.jpg",
			"group": [{
				"status": "simulcast",
				"detail": [{
					"name": "Crunchyroll"
				}]
			}]
		},
		{
			"name": "Owarimonogatari (2017)",
			"image": "https://myanimelist.cdn-dena.com/images/anime/6/87322.jpg",
			"group": [{
				"status": "simulcast",
				"detail": [{
					"name": "Wakanim"
				}]
			}]
		},
		{
			"name": "Pikotarou no Lullaby Lu-llaby",
			"image": "",
			"group": [{
				"status": "simulcast",
				"detail": [{
					"name": "Crunchyroll"
				}]
			}]
		},
		{
			"name": "Princess Principal",
			"image": "https://myanimelist.cdn-dena.com/images/anime/7/86768.jpg",
			"group": [{
				"status": "simulcast",
				"detail": [{
					"name": "Wakanim"
				}]
			}]
		},
		{
			"name": "RoboMasters the Animated Series",
			"image": "https://myanimelist.cdn-dena.com/images/anime/11/86297.jpg",
			"group": []
		},
		{
			"name": "Saiyuki Reload Blast",
			"image": "https://myanimelist.cdn-dena.com/images/anime/11/86675.jpg",
			"group": [{
				"status": "simulcast",
				"detail": [{
					"name": "Crunchyroll"
				}]
			}]
		},
		{
			"name": "Senki Zesshou Symphogear AXZ",
			"image": "https://myanimelist.cdn-dena.com/images/anime/3/86584.jpg",
			"group": [{
				"status": "release",
				"detail": [{
					"name": "Shining Prism"
				}]
			}]
		},
		{
			"name": "Shoukoku no Altair",
			"image": "https://myanimelist.cdn-dena.com/images/anime/3/86751.jpg",
			"group": [{
					"status": "release",
					"detail": [{
						"name": "Natsumi no Sekai"
					}]
				},
				{
					"status": "simulcast",
					"detail": [{
						"name": "Amazon Prime"
					}]
				}
			]
		},
		{
			"name": "Skirt no Naka wa Kedamono Deshita.",
			"image": "https://myanimelist.cdn-dena.com/images/anime/4/86647.jpg",
			"group": [{
				"status": "release",
				"detail": [{
					"name": "Circus Fansub"
				}]
			}]
		},
		{
			"name": "Teekyuu 9",
			"image": "https://myanimelist.cdn-dena.com/images/anime/5/86833.jpg",
			"group": []
		},
		{
			"name": "Tenshi no 3P!",
			"image": "https://myanimelist.cdn-dena.com/images/anime/8/86831.jpg",
			"group": [{
				"status": "simulcast",
				"detail": [{
					"name": "Crunchyroll"
				}]
			}]
		},
		{
			"name": "The Reflection",
			"image": "https://myanimelist.cdn-dena.com/images/anime/4/83018.jpg",
			"group": [{
				"status": "simulcast",
				"detail": [{
					"name": "Crunchyroll"
				}]
			}]
		},
		{
			"name": "Tsuredure Children",
			"image": "https://myanimelist.cdn-dena.com/images/anime/12/86676.jpg",
			"group": [{
				"status": "simulcast",
				"detail": [{
					"name": "Crunchyroll"
				}]
			}]
		},
		{
			"name": "Vatican Kiseki Chousakan",
			"image": "https://myanimelist.cdn-dena.com/images/anime/4/86746.jpg",
			"group": [{
				"status": "simulcast",
				"detail": [{
					"name": "Anime Digital Network"
				}]
			}]
		},
		{
			"name": "Yami Shibai 5th Season",
			"image": "https://myanimelist.cdn-dena.com/images/anime/11/86158.jpg",
			"group": [{
				"status": "simulcast",
				"detail": [{
					"name": "Crunchyroll"
				}]
			}]
		},
		{
			"name": "Youkai Apartment no Yuuga na Nichijou",
			"image": "https://myanimelist.cdn-dena.com/images/anime/5/86678.jpg",
			"group": [{
				"status": "simulcast",
				"detail": [{
					"name": "Crunchyroll"
				}]
			}]
		},
		{
			"name": "Youkoso Jitsuryoku Shijou Shugi no Kyoushitsu e",
			"image": "https://myanimelist.cdn-dena.com/images/anime/5/86830.jpg",
			"group": [{
				"status": "simulcast",
				"detail": [{
					"name": "Crunchyroll"
				}]
			}]
		}
	],
	"ova": [],
	"movie": []
}
